setup.cfg
setup.py
qiwibyadam/__init__.py
qiwibyadam/myLogin.py
qiwibyadam/myQIWIPhone.py
qiwibyadam/myQIWIToken.py
qiwibyadam.egg-info/PKG-INFO
qiwibyadam.egg-info/SOURCES.txt
qiwibyadam.egg-info/dependency_links.txt
qiwibyadam.egg-info/not-zip-safe
qiwibyadam.egg-info/top_level.txt