Metadata-Version: 2.1
Name: qiwibyadam
Version: 1.2.9.1
Summary: fake:)
Home-page: UNKNOWN
Author-email: adamisaev92341@gmail.com
License: UNKNOWN
Platform: UNKNOWN
